urdfenvs/__init__.py
urdfenvs/assets/panda/panda_scene_temp.xml
urdfenvs/generic_mujoco/__init__.py
urdfenvs/generic_mujoco/generic_mujoco_env.py
urdfenvs/generic_mujoco/generic_mujoco_robot.py
urdfenvs/keyboard_input/.gitignore
urdfenvs/keyboard_input/keyboard_input_responder.py
urdfenvs/robots/generic_urdf/__init__.py
urdfenvs/robots/generic_urdf/generic_diff_drive_robot.py
urdfenvs/robots/generic_urdf/generic_urdf_reacher.py
urdfenvs/robots/iris/__init__.py
urdfenvs/robots/iris/iris.py
urdfenvs/scene_examples/goal.py
urdfenvs/scene_examples/obstacle_data/duck.obj
urdfenvs/scene_examples/obstacle_data/duck.urdf
urdfenvs/scene_examples/obstacle_data/duck_vhacd.obj
urdfenvs/scene_examples/obstacle_data/sphere_goal.urdf
urdfenvs/scene_examples/obstacle_data/sphere_smooth.obj
urdfenvs/scene_examples/obstacles.py
urdfenvs/sensors/.gitignore
urdfenvs/sensors/__init__.py
urdfenvs/sensors/free_space_occupancy.py
urdfenvs/sensors/fsd.py
urdfenvs/sensors/fsd_sensor.py
urdfenvs/sensors/full_sensor.py
urdfenvs/sensors/grid_sensor.py
urdfenvs/sensors/lidar.py
urdfenvs/sensors/lidar_3d.py
urdfenvs/sensors/mujoco/free_space_decomposition.py
urdfenvs/sensors/mujoco/fsd_sensor.py
urdfenvs/sensors/mujoco/lidar.py
urdfenvs/sensors/mujoco/occupancy_sensor.py
urdfenvs/sensors/mujoco_interface.py
urdfenvs/sensors/obstacle_sensor.py
urdfenvs/sensors/occupancy_sensor.py
urdfenvs/sensors/physics_engine_interface.py
urdfenvs/sensors/pybullet/free_space_decomposition.py
urdfenvs/sensors/pybullet/fsd_sensor.py
urdfenvs/sensors/pybullet/lidar.py
urdfenvs/sensors/pybullet/occupancy_sensor.py
urdfenvs/sensors/pybullet_interface.py
urdfenvs/sensors/sdf_sensor.py
urdfenvs/sensors/sensor.py
urdfenvs/urdf_common/.gitignore
urdfenvs/urdf_common/__init__.py
urdfenvs/urdf_common/bicycle_model.py
urdfenvs/urdf_common/differential_drive_robot.py
urdfenvs/urdf_common/generic_robot.py
urdfenvs/urdf_common/helpers.py
urdfenvs/urdf_common/holonomic_robot.py
urdfenvs/urdf_common/meshes/checker_blue.png
urdfenvs-0.10.2.dist-info/LICENSE
urdfenvs-0.10.2.dist-info/METADATA
urdfenvs-0.10.2.dist-info/WHEEL
urdfenvs-0.10.2.dist-info/RECORD
