Metadata-Version: 2.3
Name: urdfenvs
Version: 0.10.2
Summary: Simple simulation environment for robots, based on the urdf files.
License: GPL-3.0-or-later
Keywords: robotics,motion-planning,simulation
Author: Max Spahn
Author-email: m.spahn@tudelft.nl
Maintainer: Max Spahn
Maintainer-email: m.spahn@tudelft.nl
Requires-Python: >=3.10,<4.0
Classifier: License :: OSI Approved :: GNU General Public License v3 or later (GPLv3+)
Classifier: Programming Language :: Python :: 3
Classifier: Programming Language :: Python :: 3.10
Classifier: Programming Language :: Python :: 3.11
Classifier: Programming Language :: Python :: 3.12
Classifier: Programming Language :: Python :: 3.13
Provides-Extra: keyboard
Requires-Dist: deprecation (>=2.1.0,<3.0.0)
Requires-Dist: dill (>=0.3.7,<0.4.0)
Requires-Dist: gymnasium (==1.0.0.a1)
Requires-Dist: moviepy (>=1.0.3,<2.0.0)
Requires-Dist: mpscenes (>=0.4.6,<0.5.0)
Requires-Dist: robotmodels (>=0.2.0,<0.3.0)
Project-URL: Documentation, https://maxspahn.github.io/gym_envs_urdf/
Project-URL: Homepage, https://maxspahn.github.io/gym_envs_urdf/
Project-URL: Repository, https://github.com/maxspahn/gym_envs_urdf
